miniarm_core/__init__.py
miniarm_core/__main__.py
miniarm_core/client.py
miniarm_core/py.typed
miniarm_core/version.py
mini_arm-0.4.0.dist-info/LICENSE
mini_arm-0.4.0.dist-info/METADATA
mini_arm-0.4.0.dist-info/WHEEL
mini_arm-0.4.0.dist-info/entry_points.txt
mini_arm-0.4.0.dist-info/top_level.txt
mini_arm-0.4.0.dist-info/RECORD
