Metadata-Version: 2.1
Name: mini-arm
Version: 0.4.0
Summary: A Python library for controlling the Mini-Arm 6-DOF robotic arm
Author-email: Jonathan Shulgach <jshulgac@andrew.cmu.edu>
Maintainer-email: Jonathan Shulgach <jshulgac@andrew.cmu.edu>
License: MIT
Project-URL: Homepage, https://github.com/Jshulgach/Mini-Arm
Project-URL: Documentation, https://jshulgach.github.io/Mini-Arm/
Project-URL: Repository, https://github.com/Jshulgach/Mini-Arm
Project-URL: Issues, https://github.com/Jshulgach/Mini-Arm/issues
Project-URL: Changelog, https://github.com/Jshulgach/Mini-Arm/blob/main/CHANGELOG.md
Keywords: robotics,robot-arm,mini-arm,serial,pico,circuitpython,6dof,inverse-kinematics
Classifier: Development Status :: 4 - Beta
Classifier: Intended Audience :: Developers
Classifier: Intended Audience :: Education
Classifier: Intended Audience :: Science/Research
Classifier: Operating System :: OS Independent
Classifier: Programming Language :: Python :: 3
Classifier: Programming Language :: Python :: 3.8
Classifier: Programming Language :: Python :: 3.9
Classifier: Programming Language :: Python :: 3.10
Classifier: Programming Language :: Python :: 3.11
Classifier: Programming Language :: Python :: 3.12
Classifier: Topic :: Scientific/Engineering
Classifier: Topic :: Software Development :: Libraries :: Python Modules
Requires-Python: >=3.8
License-File: LICENSE
Requires-Dist: pyserial>=3.5
Requires-Dist: numpy>=1.20.0
Provides-Extra: dev
Requires-Dist: pytest>=7.0; extra == "dev"
Requires-Dist: pytest-cov>=4.0; extra == "dev"
Requires-Dist: black>=23.0; extra == "dev"
Requires-Dist: ruff>=0.1.0; extra == "dev"
Requires-Dist: mypy>=1.0; extra == "dev"
Requires-Dist: pre-commit>=3.0; extra == "dev"
Provides-Extra: docs
Requires-Dist: sphinx>=7.0; extra == "docs"
Requires-Dist: furo>=2024.1.0; extra == "docs"
Requires-Dist: myst-parser>=2.0; extra == "docs"
Requires-Dist: sphinx-copybutton>=0.5; extra == "docs"
Requires-Dist: sphinx-autodoc-typehints>=1.25; extra == "docs"
Provides-Extra: xbox
Requires-Dist: pygame>=2.5.0; extra == "xbox"
Provides-Extra: visualization
Requires-Dist: matplotlib>=3.5.0; extra == "visualization"
Requires-Dist: roboticstoolbox-python>=1.0; extra == "visualization"
